deadset/__init__.py
deadset/deadset.py
deadset-0.2.dist-info/LICENSE
deadset-0.2.dist-info/METADATA
deadset-0.2.dist-info/WHEEL
deadset-0.2.dist-info/top_level.txt
deadset-0.2.dist-info/RECORD
