Metadata-Version: 2.1
Name: deadset
Version: 0.2
Summary: Deadset is a Python 3 module that implements expiration for Redis Keys items.
Home-page: https://github.com/buanzo/deadset
Author: Arturo "Buanzo" Busleiman
Author-email: buanzo@buanzo.com.ar
License: UNKNOWN
Platform: UNKNOWN
Requires-Python: >=3.6
Requires-Dist: redis (==3.3.11)
